zionai_utils/__init__.py
zionai_utils/client.py
zionai_utils/secrets_manager.py
zionai_utils-1.2.0.dist-info/licenses/LICENSE.md
zionai_utils-1.2.0.dist-info/METADATA
zionai_utils-1.2.0.dist-info/WHEEL
zionai_utils-1.2.0.dist-info/top_level.txt
zionai_utils-1.2.0.dist-info/RECORD
