Metadata-Version: 2.4
Name: zionai_utils
Version: 1.2.0
Summary: Enterprise AI utilities for Google Cloud Storage and Secrets Manager operations
Home-page: https://github.com/ZionClouds/zionai-utils
Author: Harshith Gundela
Author-email: harshith.gundela@zionclouds.com
License: MIT
Project-URL: Bug Reports, https://github.com/ZionClouds/zionai-utils/issues
Project-URL: Source, https://github.com/ZionClouds/zionai-utils
Project-URL: Documentation, https://pypi.org/project/zionai-utils/
Keywords: google-cloud-storage,gcs,secrets-manager,google-cloud,utility,zionai,enterprise,ai,cloud
Classifier: Development Status :: 4 - Beta
Classifier: Intended Audience :: Developers
Classifier: Operating System :: OS Independent
Classifier: Programming Language :: Python :: 3
Classifier: Programming Language :: Python :: 3.7
Classifier: Programming Language :: Python :: 3.8
Classifier: Programming Language :: Python :: 3.9
Classifier: Programming Language :: Python :: 3.10
Classifier: Programming Language :: Python :: 3.11
Classifier: Programming Language :: Python :: 3.12
Classifier: Topic :: Software Development :: Libraries :: Python Modules
Classifier: Topic :: Internet :: WWW/HTTP
Classifier: Topic :: System :: Systems Administration
Requires-Python: >=3.7
License-File: LICENSE.md
Requires-Dist: google-cloud-storage>=2.0.0
Requires-Dist: google-cloud-secret-manager>=2.0.0
Dynamic: author
Dynamic: author-email
Dynamic: classifier
Dynamic: description
Dynamic: description-content-type
Dynamic: home-page
Dynamic: keywords
Dynamic: license
Dynamic: license-file
Dynamic: project-url
Dynamic: requires-dist
Dynamic: requires-python
Dynamic: summary
